Workbook

Sheet Data
A1: Date | C1: Adjusted Closing Prices | K1: Returns | R1: Monthly rf
A2: Tickers | C2: NTPC | D2: ADANI POWER | E2: TATA POWER | F2: JSW ENERGY | G2: NHPC | H2: POWERGRID | I2: Nifty50 | K2: NTPC | L2: ADANI POWER | M2: TATA POWER | N2: JSW ENERGY | O2: NHPC | P2: POWERGRID | Q2: Nifty50
A3: 44200 | C3: 85.41214 | D3: 94.75 | E3: 95.52217 | F3: 106.7203 | G3: 20.7731 | H3: 100.7787 | I3: 14631.1 | R3: 6.03
A4: 44201 | C4: 92.1234 | D4: 92.5 | E4: 102.8663 | F4: 114.6562 | G4: 22.27219 | H4: 103.3434 | I4: 15582.8 | K4: =LN(C4/C3) -> 0.075640737 | L4: =LN(D4/D3) -> -0.024033199 | M4: =LN(E4/E3) -> 0.07407172 | N4: =LN(F4/F3) -> 0.071726692 | O4: =LN(G4/G3) -> 0.069679935 | P4: =LN(H4/H3) -> 0.0251304 | Q4: =LN(I4/I3) -> 0.063018342 | R4: 6.022
A5: 44202 | C5: 97.0422 | D5: 113.45 | E5: 117.9894 | F5: 163.3425 | G5: 22.44352 | H5: 106.4348 | I5: 15721.5 | K5: =LN(C5/C4) -> 0.052016953 | L5: =LN(D5/D4) -> 0.20415357 | M5: =LN(E5/E4) -> 0.1371647 | N5: =LN(F5/F4) -> 0.35391114 | O5: =LN(G5/G4) -> 0.0076631161 | P5: =LN(H5/H4) -> 0.029475168 | Q5: =LN(I5/I4) -> 0.0088614604 | R5: 6.051
A6: 44203 | C6: 98.54284 | D6: 95.85 | E6: 122.2969 | F6: 245.9144 | G6: 22.48635 | H6: 104.5113 | I6: 15763.05 | K6: =LN(C6/C5) -> 0.015345442 | L6: =LN(D6/D5) -> -0.16857774 | M6: =LN(E6/E5) -> 0.035856905 | N6: =LN(F6/F5) -> 0.40913428 | O6: =LN(G6/G5) -> 0.0019065273 | P6: =LN(H6/H5) -> -0.018237392 | Q6: =LN(I6/I5) -> 0.0026393913 | R6: 6.204
A7: 44204 | C7: 96.66703 | D7: 98.5 | E7: 126.2593 | F7: 259.8525 | G7: 23.08599 | H7: 107.0759 | I7: 17132.2 | K7: =LN(C7/C6) -> -0.019218985 | L7: =LN(D7/D6) -> 0.027272079 | M7: =LN(E7/E6) -> 0.031886034 | N7: =LN(F7/F6) -> 0.055130654 | O7: =LN(G7/G6) -> 0.026317482 | P7: =LN(H7/H6) -> 0.024242729 | Q7: =LN(I7/I6) -> 0.08329114 | R7: 6.215
A8: 44205 | C8: 118.2598 | D8: 97.1 | E8: 155.317 | F8: 382.832 | G8: 25.57019 | H8: 115.9608 | I8: 17618.15 | K8: =LN(C8/C7) -> 0.20161151 | L8: =LN(D8/D7) -> -0.014315173 | M8: =LN(E8/E7) -> 0.20713046 | N8: =LN(F8/F7) -> 0.38748209 | O8: =LN(G8/G7) -> 0.10220128 | P8: =LN(H8/H7) -> 0.079714274 | Q8: =LN(I8/I7) -> 0.027969887 | R8: 6.223
A9: 44206 | C9: 116.65 | D9: 100.5 | E9: 209.6657 | F9: 342.3297 | G9: 26.63181 | H9: 114.9933 | I9: 17671.65 | K9: =LN(C9/C8) -> -0.013705901 | L9: =LN(D9/D8) -> 0.034416352 | M9: =LN(E9/E8) -> 0.30004617 | N9: =LN(F9/F8) -> -0.11182194 | O9: =LN(G9/G8) -> 0.040679146 | P9: =LN(H9/H8) -> -0.0083783372 | Q9: =LN(I9/I8) -> 0.0030320399 | R9: 6.388
A10: 44207 | C10: 111.9014 | D10: 99.35 | E10: 212.1117 | F10: 282.0919 | G10: 26.97881 | H10: 128.478 | I10: 16983.2 | K10: =LN(C10/C9) -> -0.041559872 | L10: =LN(D10/D9) -> -0.011508759 | M10: =LN(E10/E9) -> 0.011598665 | N10: =LN(F10/F9) -> -0.1935414 | O10: =LN(G10/G9) -> 0.012945377 | P10: =LN(H10/H9) -> 0.11088382 | Q10: =LN(I10/I9) -> -0.03973704 | R10: 6.326
A11: 44208 | C11: 109.3951 | D11: 99.7 | E11: 216.1719 | F11: 295.0526 | G11: 26.84869 | H11: 127.0177 | I11: 17354.05 | K11: =LN(C11/C10) -> -0.022652027 | L11: =LN(D11/D10) -> 0.003516708 | M11: =LN(E11/E10) -> 0.018960902 | N11: =LN(F11/F10) -> 0.044920741 | O11: =LN(G11/G10) -> -0.0048347129 | P11: =LN(H11/H10) -> -0.011431237 | Q11: =LN(I11/I10) -> 0.021601288 | R11: 6.454
A12: 44562 | C12: 124.9162 | D12: 106.25 | E12: 240.7291 | F12: 300.8947 | G12: 26.02457 | H12: 135.8256 | I12: 17339.85 | K12: =LN(C12/C11) -> 0.13267701 | L12: =LN(D12/D11) -> 0.063629131 | M12: =LN(E12/E11) -> 0.10759831 | N12: =LN(F12/F11) -> 0.019606724 | O12: =LN(G12/G11) -> -0.031175938 | P12: =LN(H12/H11) -> 0.067045263 | Q12: =LN(I12/I11) -> -0.00081858775 | R12: 6.684
A13: 44563 | C13: 117.3975 | D13: 123.75 | E13: 218.2265 | F13: 334.0329 | G13: 23.76911 | H13: 131.8845 | I13: 16793.9 | K13: =LN(C13/C12) -> -0.0620775 | L13: =LN(D13/D12) -> 0.15246859 | M13: =LN(E13/E12) -> -0.098138721 | N13: =LN(F13/F12) -> 0.10447912 | O13: =LN(G13/G12) -> -0.090654253 | P13: =LN(H13/H12) -> -0.02944517 | Q13: =LN(I13/I12) -> -0.031991596 | R13: 6.77
A14: 44564 | C14: 122.179 | D14: 185.1 | E14: 233.4892 | F14: 296.7218 | G14: 25.21534 | H14: 140.5068 | I14: 17464.75 | K14: =LN(C14/C13) -> 0.03992157 | L14: =LN(D14/D13) -> 0.40263282 | M14: =LN(E14/E13) -> 0.067602309 | N14: =LN(F14/F13) -> -0.11844449 | O14: =LN(G14/G13) -> 0.059065701 | P14: =LN(H14/H13) -> 0.063329347 | Q14: =LN(I14/I13) -> 0.039168839 | R14: 6.843
A15: 44565 | C15: 141.3656 | D15: 280.35 | E15: 237.1091 | F15: 311.8917 | G15: 30.11329 | H15: 147.6034 | I15: 17102.55 | K15: =LN(C15/C14) -> 0.14586226 | L15: =LN(D15/D14) -> 0.4151426 | M15: =LN(E15/E14) -> 0.015384549 | N15: =LN(F15/F14) -> 0.049861013 | O15: =LN(G15/G14) -> 0.17751406 | P15: =LN(H15/H14) -> 0.049273061 | Q15: =LN(I15/I14) -> -0.020956989 | R15: 7.139
... A51: 45661 | C51: 349.8 | D51: 509.95 | E51: 354.85 | F51: 488.4 | G51: 82.58 | H51: 289.4 | I51: 22161.6 | K51: =LN(C51/C50) -> -0.022053481 | L51: =LN(D51/D50) -> 0.0012754478 | M51: =LN(E51/E50) -> -0.056296959 | N51: =LN(F51/F50) -> -0.096537927 | O51: =LN(G51/G50) -> 0.0046122184 | P51: =LN(H51/H50) -> -0.0032772776 | Q51: =LN(I51/I50) -> -0.059462425 | R51: 6.575
A55: Company | B55: Beta (By Regression) | C55: Debt to Equity Ratio | D55: Tax Rate | E55: Unlevered Beta | I55: Market Return | J55: Risk Free Rate
A56: NTPC | B56: =NTPC!B11 -> 1.0881 | C56: ='D TO E'!G2 -> 1.394 | D56: 0.3 | E56: =B56/((1+(1-D56)*C56)) -> 0.55071363 | H56: Average Return | I56: =AVERAGE(Q3:Q51) -> 0.0086502429 | J56: =AVERAGE(R3:R51)/100 -> 0.069137347
A57: ADANIPOWER | B57: =ADANIPOWER!B11 -> 1.2727 | C57: ='D TO E'!G3 -> 1.784 | D57: 0.3 | E57: =B57/((1+(1-D57)*C57)) -> 0.56594628 | H57: Annualised Return | I57: =(1+I56)^12-1 -> 0.10888669 | J57: =J56 -> 0.069137347
A58: TATAPOWER | B58: =TATAPOWER!B11 -> 1.3879 | C58: ='D TO E'!G4 -> 1.718 | D58: 0.3 | E58: =B58/((1+(1-D58)*C58)) -> 0.63011895
A59: JSW ENERGY | B59: ='JSW ENERGY'!B11 -> 1.7603 | C59: ='D TO E'!G5 -> 0.424 | D59: 0.3 | E59: =B59/((1+(1-D59)*C59)) -> 1.3574183
A60: NHPC | B60: =NHPC!B11 -> 1.1168 | C60: ='D TO E'!G6 -> 0.824 | D60: 0.3 | E60: =B60/((1+(1-D60)*C60)) -> 0.70826991
A61: POWERGRID | B61: =POWERGRID!B11 -> 0.9661 | C61: ='D TO E'!G7 -> 1.608 | D61: 0.3 | E61: =B61/((1+(1-D61)*C61)) -> 0.45450696

Sheet NTPC
A1: SUMMARY OUTPUT
A3: Regression Statistics
A4: R Square | B4: 0.327
A5: Adjusted R Square | B5: 0.313
A6: Observations | B6: 48
B9: Coefficients | C9: Standard Error | D9: t Stat | E9: P-value | F9: Lower 95% | G9: Upper 95%
A10: Intercept | B10: 0.0198 | C10: 0.009 | D10: 2.219 | E10: 0.031 | F10: 0.002 | G10: 0.038
A11: X Variable 1 | B11: 1.0881 | C11: 0.23 | D11: 4.731 | E11: 0 | F11: 0.625 | G11: 1.551

Sheet ADANIPOWER
A1: SUMMARY OUTPUT
A3: Regression Statistics
A4: R Square | B4: 0.091
A5: Adjusted R Square | B5: 0.072
A6: Observations | B6: 48
B9: Coefficients | C9: Standard Error | D9: t Stat | E9: P-value | F9: Lower 95% | G9: Upper 95%
A10: Intercept | B10: 0.0238 | C10: 0.023 | D10: 1.037 | E10: 0.305 | F10: -0.022 | G10: 0.07
A11: X Variable 1 | B11: 1.2727 | C11: 0.592 | D11: 2.15 | E11: 0.037 | F11: 0.081 | G11: 2.464

Sheet TATAPOWER
A1: SUMMARY OUTPUT
A3: Regression Statistics
A4: R Square | B4: 0.332
A5: Adjusted R Square | B5: 0.318
A6: Observations | B6: 48
B9: Coefficients | C9: Standard Error | D9: t Stat | E9: P-value | F9: Lower 95% | G9: Upper 95%
A10: Intercept | B10: 0.0152 | C10: 0.011 | D10: 1.35 | E10: 0.183 | F10: -0.007 | G10: 0.038
A11: X Variable 1 | B11: 1.3879 | C11: 0.29 | D11: 4.786 | E11: 0 | F11: 0.804 | G11: 1.972

Sheet JSW ENERGY
A1: SUMMARY OUTPUT
A3: Regression Statistics
A4: R Square | B4: 0.186
A5: Adjusted R Square | B5: 0.169
A6: Observations | B6: 48
B9: Coefficients | C9: Standard Error | D9: t Stat | E9: P-value | F9: Lower 95% | G9: Upper 95%
A10: Intercept | B10: 0.0158 | C10: 0.021 | D10: 0.75 | E10: 0.457 | F10: -0.027 | G10: 0.058
A11: X Variable 1 | B11: 1.7603 | C11: 0.542 | D11: 3.246 | E11: 0.002 | F11: 0.669 | G11: 2.852

Sheet NHPC
A1: SUMMARY OUTPUT
A3: Regression Statistics
A4: R Square | B4: 0.222
A5: Adjusted R Square | B5: 0.205
A6: Observations | B6: 48
B9: Coefficients | C9: Standard Error | D9: t Stat | E9: P-value | F9: Lower 95% | G9: Upper 95%
A10: Intercept | B10: 0.0193 | C10: 0.012 | D10: 1.61 | E10: 0.114 | F10: -0.005 | G10: 0.043
A11: X Variable 1 | B11: 1.1168 | C11: 0.308 | D11: 3.622 | E11: 0.001 | F11: 0.496 | G11: 1.737

Sheet POWERGRID
A1: SUMMARY OUTPUT
A3: Regression Statistics
A4: R Square | B4: 0.318
A5: Adjusted R Square | B5: 0.303
A6: Observations | B6: 48
B9: Coefficients | C9: Standard Error | D9: t Stat | E9: P-value | F9: Lower 95% | G9: Upper 95%
A10: Intercept | B10: 0.0141 | C10: 0.008 | D10: 1.752 | E10: 0.086 | F10: -0.002 | G10: 0.03
A11: X Variable 1 | B11: 0.9661 | C11: 0.208 | D11: 4.634 | E11: 0 | F11: 0.546 | G11: 1.386

Sheet MVE
A1: NTPC | F1: ADANI POWER | K1: TATA POWER | P1: JSW ENERGY | U1: NHPC | Z1: POWERGRID
A4: Date | B4: Adj Close | C4: Volume | D4: Mve(Monthly) | F4: Date | G4: Adj Close | H4: Volume | I4: Mve(Monthly) | K4: Date | L4: Adj Close | M4: Volume | N4: Mve(Monthly) | P4: Date | Q4: Adj Close | R4: Volume | S4: Mve(Monthly) | U4: Date | V4: Adj Close | W4: Volume | X4: Mve(Monthly) | Z4: Date | AA4: Adj Close | AB4: Volume | AC4: Mve(Monthly)
A5: 44200 | B5: 85.41214 | C5: 322068662 | D5: =B5*C5 -> 2.7508574e+10 | F5: 44200 | G5: 94.75 | H5: 391842219 | I5: =G5*H5 -> 3.712705e+10 | K5: 44200 | L5: 95.52217 | M5: 857000000 | N5: =L5*M5 -> 81862499690 | P5: 44200 | Q5: 106.7203 | R5: 217000000 | S5: =Q5*R5 -> 23158305100 | U5: 44200 | V5: 20.7731 | W5: 43501353 | X5: =V5*W5 -> 9.0365796e+08 | Z5: 44200 | AA5: 100.7787 | AB5: 342000000 | AC5: =AA5*AB5 -> 34466315400
A6: 44201 | B6: 92.1234 | C6: 384108057 | D6: =B6*C6 -> 3.538534e+10 | F6: 44201 | G6: 92.5 | H6: 321665163 | I6: =G6*H6 -> 2.9754028e+10 | K6: 44201 | L6: 102.8663 | M6: 779000000 | N6: =L6*M6 -> 80132847700 | P6: 44201 | Q6: 114.6562 | R6: 127000000 | S6: =Q6*R6 -> 14561337400 | U6: 44201 | V6: 22.27219 | W6: 166000000 | X6: =V6*W6 -> 3.6971835e+09 | Z6: 44201 | AA6: 103.3434 | AB6: 460000000 | AC6: =AA6*AB6 -> 47537964000
A7: 44202 | B7: 97.0422 | C7: 449217999 | D7: =B7*C7 -> 4.3593103e+10 | F7: 44202 | G7: 113.45 | H7: 855635884 | I7: =G7*H7 -> 9.7071891e+10 | K7: 44202 | L7: 117.9894 | M7: 1490000000 | N7: =L7*M7 -> 175804206000 | P7: 44202 | Q7: 163.3425 | R7: 185000000 | S7: =Q7*R7 -> 30218362500 | U7: 44202 | V7: 22.44352 | W7: 213000000 | X7: =V7*W7 -> 4780469760 | Z7: 44202 | AA7: 106.4348 | AB7: 461000000 | AC7: =AA7*AB7 -> 49066442800
A8: 44203 | B8: 98.54284 | C8: 267374589 | D8: =B8*C8 -> 2.6347851e+10 | F8: 44203 | G8: 95.85 | H8: 74066782 | I8: =G8*H8 -> 7.0993011e+09 | K8: 44203 | L8: 122.2969 | M8: 568000000 | N8: =L8*M8 -> 69464639200 | P8: 44203 | Q8: 245.9144 | R8: 120000000 | S8: =Q8*R8 -> 29509728000 | U8: 44203 | V8: 22.48635 | W8: 88683218 | X8: =V8*W8 -> 1.9941619e+09 | Z8: 44203 | AA8: 104.5113 | AB8: 246000000 | AC8: =AA8*AB8 -> 25709779800
A9: 44204 | B9: 96.66703 | C9: 213000640 | D9: =B9*C9 -> 2.0590139e+10 | F9: 44204 | G9: 98.5 | H9: 91458437 | I9: =G9*H9 -> 9.008656e+09 | K9: 44204 | L9: 126.2593 | M9: 688000000 | N9: =L9*M9 -> 86866398400 | P9: 44204 | Q9: 259.8525 | R9: 46897128 | S9: =Q9*R9 -> 1.2186336e+10 | U9: 44204 | V9: 23.08599 | W9: 121000000 | X9: =V9*W9 -> 2793404790 | Z9: 44204 | AA9: 107.0759 | AB9: 406000000 | AC9: =AA9*AB9 -> 43472815400
A10: 44205 | B10: 118.2598 | C10: 351704842 | D10: =B10*C10 -> 4.1592544e+10 | F10: 44205 | G10: 97.1 | H10: 100312748 | I10: =G10*H10 -> 9.7403678e+09 | K10: 44205 | L10: 155.317 | M10: 706000000 | N10: =L10*M10 -> 109653802000 | P10: 44205 | Q10: 382.832 | R10: 31778127 | S10: =Q10*R10 -> 1.2165684e+10 | U10: 44205 | V10: 25.57019 | W10: 301000000 | X10: =V10*W10 -> 7696627190 | Z10: 44205 | AA10: 115.9608 | AB10: 333000000 | AC10: =AA10*AB10 -> 38614946400
A11: 44206 | B11: 116.65 | C11: 410945318 | D11: =B11*C11 -> 4.7936771e+10 | F11: 44206 | G11: 100.5 | H11: 223376532 | I11: =G11*H11 -> 22449341466 | K11: 44206 | L11: 209.6657 | M11: 2600000000 | N11: =L11*M11 -> 5.4513082e+11 | P11: 44206 | Q11: 342.3297 | R11: 29050882 | S11: =Q11*R11 -> 9.9449797e+09 | U11: 44206 | V11: 26.63181 | W11: 299000000 | X11: =V11*W11 -> 7962911190 | Z11: 44206 | AA11: 114.9933 | AB11: 294000000 | AC11: =AA11*AB11 -> 33808030200
A12: 44207 | B12: 111.9014 | C12: 227168422 | D12: =B12*C12 -> 2.5420464e+10 | F12: 44207 | G12: 99.35 | H12: 85614034 | I12: =G12*H12 -> 8.5057543e+09 | K12: 44207 | L12: 212.1117 | M12: 1360000000 | N12: =L12*M12 -> 288471912000 | P12: 44207 | Q12: 282.0919 | R12: 33830131 | S12: =Q12*R12 -> 9.5432059e+09 | U12: 44207 | V12: 26.97881 | W12: 146000000 | X12: =V12*W12 -> 3938906260 | Z12: 44207 | AA12: 128.478 | AB12: 311000000 | AC12: =AA12*AB12 -> 39956658000
A13: 44208 | B13: 109.3951 | C13: 264909689 | D13: =B13*C13 -> 2.8979822e+10 | F13: 44208 | G13: 99.7 | H13: 77906843 | I13: =G13*H13 -> 7.7673122e+09 | K13: 44208 | L13: 216.1719 | M13: 724000000 | N13: =L13*M13 -> 156508455600 | P13: 44208 | Q13: 295.0526 | R13: 16850855 | S13: =Q13*R13 -> 4.9718886e+09 | U13: 44208 | V13: 26.84869 | W13: 198000000 | X13: =V13*W13 -> 5316040620 | Z13: 44208 | AA13: 127.0177 | AB13: 474000000 | AC13: =AA13*AB13 -> 60206389800
A14: 44562 | B14: 124.9162 | C14: 293504871 | D14: =B14*C14 -> 3.6663513e+10 | F14: 44562 | G14: 106.25 | H14: 262717406 | I14: =G14*H14 -> 2.7913724e+10 | K14: 44562 | L14: 240.7291 | M14: 640000000 | N14: =L14*M14 -> 154066624000 | P14: 44562 | Q14: 300.8947 | R14: 15590406 | S14: =Q14*R14 -> 4.6910705e+09 | U14: 44562 | V14: 26.02457 | W14: 101000000 | X14: =V14*W14 -> 2628481570 | Z14: 44562 | AA14: 135.8256 | AB14: 310000000 | AC14: =AA14*AB14 -> 42105936000
A15: 44563 | B15: 117.3975 | C15: 206605031 | D15: =B15*C15 -> 2.4254914e+10 | F15: 44563 | G15: 123.75 | H15: 1201401558 | I15: =G15*H15 -> 1.4867344e+11 | K15: 44563 | L15: 218.2265 | M15: 785000000 | N15: =L15*M15 -> 171307802500 | P15: 44563 | Q15: 334.0329 | R15: 12705982 | S15: =Q15*R15 -> 4.244216e+09 | U15: 44563 | V15: 23.76911 | W15: 79391826 | X15: =V15*W15 -> 1.887073e+09 | Z15: 44563 | AA15: 131.8845 | AB15: 266000000 | AC15: =AA15*AB15 -> 35081277000
A16: 44564 | B16: 122.179 | C16: 254347602 | D16: =B16*C16 -> 3.1075936e+10 | F16: 44564 | G16: 185.1 | H16: 1117006956 | I16: =G16*H16 -> 2.0675799e+11 | K16: 44564 | L16: 233.4892 | M16: 448000000 | N16: =L16*M16 -> 104603161600 | P16: 44564 | Q16: 296.7218 | R16: 10302606 | S16: =Q16*R16 -> 3.0570078e+09 | U16: 44564 | V16: 25.21534 | W16: 190000000 | X16: =V16*W16 -> 4790914600 | Z16: 44564 | AA16: 140.5068 | AB16: 368000000 | AC16: =AA16*AB16 -> 51706502400
... A53: 45661 | B53: 349.8 | C53: 71545262 | D53: =B53*C53 -> 2.5026533e+10 | F53: 45661 | G53: 509.95 | H53: 30710720 | I53: =G53*H53 -> 15660931664 | K53: 45661 | L53: 354.85 | M53: 30793825 | N53: =L53*M53 -> 1.0927189e+10 | P53: 45661 | Q53: 488.4 | R53: 19858226 | S53: =Q53*R53 -> 9.6987576e+09 | U53: 45661 | V53: 82.58 | W53: 107000000 | X53: =V53*W53 -> 8836060000 | Z53: 45661 | AA53: 289.4 | AB53: 90630391 | AC53: =AA53*AB53 -> 2.6228435e+10
A56: Avg MVE= | B56: =AVERAGE(D5:D53) -> 6.8857454e+10 | F56: Avg MVE= | G56: =AVERAGE(I5:I53) -> 7.0276369e+10 | K56: Avg MVE= | L56: =AVERAGE(N5:N53) -> 1.0922065e+11 | P56: Avg MVE= | Q56: =AVERAGE(S5:S53) -> 2.5789437e+10 | U56: Avg MVE= | V56: =AVERAGE(X5:X53) -> 4.3184863e+10 | Z56: Avg MVE= | AA56: =AVERAGE(AC5:AC53) -> 6.3429653e+10

Sheet D TO E
A1: Companies | B1: 2025 D/E | C1: 2024 D/E | D1: 2023 D/E | E1: 2022 D/E | F1: 2021 D/E | G1: AVG D/E
A2: NTPC | B2: 1.43 | C2: 1.24 | D2: 1.34 | E2: 1.5 | F2: 1.46 | G2: 1.394
A3: ADANI POWER | B3: 0.67 | C3: 0.62 | D3: 1.32 | E3: 2.45 | F3: 3.86 | G3: 1.784
A4: TATA POWER | B4: 1.73 | C4: 1.41 | D4: 1.57 | E4: 2 | F4: 1.88 | G4: 1.718
A5: JSW ENERGY | B5: 0.97 | C5: 0.46 | D5: 0.46 | E5: 0.09 | F5: 0.14 | G5: 0.424
A6: NHPC | B6: 0.79 | C6: 0.84 | D6: 0.85 | E6: 0.84 | F6: 0.8 | G6: 0.824
A7: POWERGIRD | B7: 1.33 | C7: 1.42 | D7: 1.56 | E7: 1.7 | F7: 2.03 | G7: 1.608

Sheet Cost of debt
A1: Period | B1: 45741 | C1: 45740 | D1: 45739 | E1: 45738 | F1: 45737 | I1: Cost of Debt for NTPC
A2: EBIT | B2: 35948.3 | C2: 38554.26 | D2: 34864.73 | E2: 31038.98 | F2: 26665.91
A3: Interest Expense | B3: 12700 | C3: 12048.21 | D3: 11156.06 | E3: 9315.98 | F3: 9224.14 | J3: Avg. Interest Coverage Ratio
B4: =B2/B3 -> 2.8305748 | J4: 3.1738
A6: Interest Coverage | I6: Spread Value | J6: 0.035
A7: Period | B7: 45741 | C7: 45740 | D7: 45739 | E7: 45738 | F7: 45737 | I7: Risk Free Rate | J7: 6.914
A8: Interest Coverage | B8: 3.35 | C8: 3.256 | D8: 3.177 | E8: 3.312 | F8: 2.774 | I8: Pre Tax Cost of Debt= | J8: 10.414
I10: Weight of Equity= | J10: 0.40395427
A11: D/E for NTPC | B11: 1.4755277 | I11: Weight of Debt= | J11: 0.59604572
A12: D/V for NTPC | B12: 0.59604572
A13: E/V for NTPC | B13: 0.40395427

Sheet WACC using Top Down Approach (E
A1: SUMMARY OUTPUT
A3: Regression Statistics
A4: R Square | B4: 0.327
A5: Adjusted R Square | B5: 0.313
A6: Observations | B6: 48
B9: Coefficients | C9: Standard Error | D9: t Stat | E9: P-value | F9: Lower 95% | G9: Upper 95%
A10: Intercept | B10: 0.0198 | C10: 0.009 | D10: 2.219 | E10: 0.031 | F10: 0.002 | G10: 0.038
A11: X Variable 1 | B11: 1.0881 | C11: 0.23 | D11: 4.731 | E11: 0 | F11: 0.625 | G11: 1.551
A14: Risk Free Rate | B14: 0.0675
A15: Market Return | B15: 0.10889
A16: Cost of Equity | B16: =B14+(B11*(B15-B14)) -> 0.11253646
A17: Cost of Debt | B17: 0.10414
A18: D/E | B18: 1.4755277
A19: E/V | B19: 0.40395427
A20: D/V | B20: 0.59604572
A21: Tax Rate | B21: 0.3
A22: WACC | B22: =(B19*B16)+(B20*(1-B21)*B17) -> 0.088910125

Sheet WACC using Bottom Up Approach (
A2: Company | B2: Beta (By Regression) | C2: Debt to Equity Ratio | D2: Tax Rate | E2: Unlevered Beta
A3: NTPC | B3: =NTPC!B11 -> 1.0881 | C3: ='D TO E'!G2 -> 1.394 | D3: 0.3 | E3: =B3/((1+(1-D3)*C3)) -> 0.55071363
A4: ADANIPOWER | B4: =ADANIPOWER!B11 -> 1.2727 | C4: ='D TO E'!G3 -> 1.784 | D4: 0.3 | E4: =B4/((1+(1-D4)*C4)) -> 0.56594628
A5: TATAPOWER | B5: =TATAPOWER!B11 -> 1.3879 | C5: ='D TO E'!G4 -> 1.718 | D5: 0.3 | E5: =B5/((1+(1-D5)*C5)) -> 0.63011895
A6: JSW ENERGY | B6: ='JSW ENERGY'!B11 -> 1.7603 | C6: ='D TO E'!G5 -> 0.424 | D6: 0.3 | E6: =B6/((1+(1-D6)*C6)) -> 1.3574183 | I6: Market Return | J6: Risk Free Rate
A7: NHPC | B7: =NHPC!B11 -> 1.1168 | C7: ='D TO E'!G6 -> 0.824 | D7: 0.3 | E7: =B7/((1+(1-D7)*C7)) -> 0.70826991 | H7: Average Return | I7: =Data!I56 -> 0.0086502429 | J7: =Data!J56 -> 0.069137347
A8: POWERGRID | B8: =POWERGRID!B11 -> 0.9661 | C8: ='D TO E'!G7 -> 1.608 | D8: 0.3 | E8: =B8/((1+(1-D8)*C8)) -> 0.45450696 | H8: Annualised Return | I8: =Data!I57 -> 0.10888669 | J8: =J7 -> 0.069137347
H12: Pre Tax Cost of Debt= | I12: 0.10414
A13: Average of Unlevered Beta for Comparable Firms | D13: =AVERAGE(E4:E18) -> 0.74325207
A16: Market Value of D/E for Target Company | D16: =C3 -> 1.394
A18: Relevered Beta of the Target Company | D18: =D13*(1+(1-D3)*D16) -> 1.4685174
A20: Cost of Equity Capital | D20: =J8+(D18*(I12-J8)) -> 0.12053935
A22: D/E for NTPC | D22: 1.4755277
A23: D/V for NTPC | D23: 0.59604572
A24: E/V for NTPC | D24: 0.40395427
A26: WACC | D26: =D24*D20+D23*(1-D3)*I12 -> 0.092142928

Sheet Financial statements
A2: NTPC | O2: ADANI POWER
A4: Income Statement | H4: Balance sheet | O4: Income Statement | V4: Balance sheet
B5: 45740 | C5: 45739 | D5: 45738 | E5: 45737 | F5: 45736 | I5: 45740 | J5: 45739 | K5: 45738 | L5: 45737 | M5: 45736 | P5: 45741 | Q5: 45740 | R5: 45739 | S5: 45738 | T5: 45737 | W5: 45376 | X5: 45740 | Y5: 45739 | Z5: 45738 | AA5: 45737
A6: Total Revenue/Income | B6: 178500 | C6: 176206 | D6: 132669 | E6: 111531 | F6: 101422
A7: Cost Of Revenue | B7: 103994 | C7: 105980 | D7: 75337.66 | E7: 66045.32 | F7: 62954.03 | H7: EQUITIES AND LIABILITIES | O7: Total Revenue/Income | P7: 50351.25 | Q7: 38773.3 | R7: 27711.18 | S7: 26221.48 | T7: 26467.72 | V7: EQUITIES AND LIABILITIES
A8: Gross Profit | B8: 74506.13 | C8: 70226.2 | D8: 57331.62 | E8: 45989.08 | F8: 44341.59 | H8: SHAREHOLDER'S FUNDS | O8: Cost Of Revenue | P8: 29178.89 | Q8: 26214.6 | R8: 15950.54 | S8: 16613.23 | T8: 18921.51 | V8: SHAREHOLDER'S FUNDS
A9: Total Operating Expense | B9: 155660 | C9: 154426 | D9: 115493 | E9: 99231.77 | F9: 82062.54 | H9: Equity Share Capital | I9: 9696.67 | J9: 9696.67 | K9: 9696.67 | L9: 9696.67 | M9: 9894.56 | O9: Gross Profit | P9: 21172.36 | Q9: 12558.7 | R9: 11760.64 | S9: 9608.25 | T9: 7546.21 | V9: Equity Share Capital | W9: 3856.94 | X9: 3856.94 | Y9: 3856.94 | Z9: 3856.94 | AA9: 3856.94
A10: Selling General Administrative Expenses | B10: 0 | C10: 13220.52 | D10: 6310.09 | E10: 528.2 | F10: 8758.52 | H10: Total Share Capital | I10: 9696.67 | J10: 9696.67 | K10: 9696.67 | L10: 9696.67 | M10: 9894.56 | O10: Total Operating Expense | P10: 39489.97 | Q10: 35365.82 | R10: 25109.34 | S10: 25860.94 | T10: 23174.19 | V10: Preference Share Capital | W10: 184.49 | X10: 168.95 | Y10: 154.43 | Z10: 0 | AA10: 0
A11: Other Operating Expenses | B11: 155660 | C11: 138208 | D11: 11021.47 | E11: 90377.95 | F11: 8317.94 | H11: Reserves and Surplus | I11: 1,40,188.35 | J11: 1,29,193.21 | K11: 1,18,354.40 | L11: 1,09,288.82 | M11: 1,03,674.88 | O11: Selling General Administrative Expenses | P11: 0 | Q11: 569.99 | R11: 470.31 | S11: 163.51 | T11: 1516.53 | V11: Total Share Capital | W11: 4041.43 | X11: 4025.89 | Y11: 4011.37 | Z11: 3856.94 | AA11: 3856.94
A12: Sell And Marketing Exp | B12: 0 | C12: 2760.89 | D12: 0 | E12: 1185.56 | F12: 0 | H12: Total Reserves and Surplus | I12: 1,40,188.35 | J12: 1,29,193.21 | K12: 1,18,354.40 | L12: 1,09,288.82 | M12: 1,03,674.88 | O12: Other Operating Expenses | P12: 39488.89 | Q12: 34795.83 | R12: 24639.03 | S12: 20389.79 | T12: 568.48 | V12: Reserves and Surplus | W12: 28029.56 | X12: 10905.38 | Y12: 1145.4 | Z12: 4213.41 | AA12: 3318.44
A13: Research & Development | B13: 0 | C13: 236.78 | D13: 0 | E13: 0 | F13: 0 | H13: Total Shareholders Funds | I13: 1,49,885.02 | J13: 1,38,889.88 | K13: 1,28,051.07 | L13: 1,18,985.49 | M13: 1,13,569.44 | O13: Research & Development | P13: 1.08 | Q13: 0 | R13: 0 | S13: 0 | T13: 0 | V13: Total Reserves and Surplus | W13: 28029.56 | X13: 10905.38 | Y13: 1145.4 | Z13: 4213.41 | AA13: 3318.44
A14: Depreciation And Amortization | B14: 16203.63 | C14: 14792.27 | D14: 13787.83 | E14: 12450.31 | F14: 10356.16 | H14: NON-CURRENT LIABILITIES | O14: Depreciation And Amortization | P14: 3931.33 | Q14: 3303.68 | R14: 3117.54 | S14: 3201.65 | T14: 3006.5 | V14: Total Shareholders Funds | W14: 32070.99 | X14: 14931.27 | Y14: 5156.77 | Z14: 8070.35 | AA14: 7175.38
A15: Operating Income/Profit | B15: 22840.87 | C15: 32936.64 | D15: 26491.73 | E15: 21656.45 | F15: 22207.07 | H15: Long Term Borrowings | I15: 1,46,159.07 | J15: 1,56,315.69 | K15: 1,47,374.75 | L15: 1,51,229.62 | M15: 1,46,538.70 | O15: Operating Income/Profit | P15: 10861.28 | Q15: 6740.98 | R15: 6696.62 | S15: 5831.69 | T15: 1920.57 | V15: Hybrid/Debt/Other Securities | W15: 7561.55 | X15: 13461.55 | Y15: 13461.55 | Z15: 9015 | AA15: 8615
A16: Interest Income | B16: 0 | C16: -10355.33 | D16: 8295.85 | E16: 8540.17 | F16: -8449.04 | H16: Deferred Tax Liabilities [Net] | I16: 13066.53 | J16: 10614.07 | K16: 10006.29 | L16: 9160.99 | M16: 8093.98 | O16: Interest Income | P16: 0 | Q16: -3333.5 | R16: 4094.78 | S16: 5106.33 | T16: -3935.85 | V16: NON-CURRENT LIABILITIES
A17: Total Other Income Expense Net | B17: -6747.43 | C17: -11156.06 | D17: -5970.82 | E17: 6169.71 | F17: 0 | H17: Other Long Term Liabilities | I17: 1373.39 | J17: 1391.89 | K17: 2786.77 | L17: 2582.49 | M17: 1262.13 | O17: Total Other Income Expense Net | P17: -3388.09 | Q17: -2958.49 | R17: -119.49 | S17: 3542.95 | T17: 0 | V17: Long Term Borrowings | W17: 18701.13 | X17: 24809.68 | Y17: 30308.02 | Z17: 930.56 | AA17: 3112.85
A18: EBITDA | B18: 54757.89 | C18: 49657 | D18: 43624.72 | E18: 39116.22 | F18: 34032.16 | H18: Long Term Provisions | I18: 1898.03 | J18: 1727.78 | K18: 1446.02 | L18: 826.25 | M18: 826.74 | O18: EBITDA | P18: 28110.93 | Q18: 14311.88 | R18: 13789.45 | S18: 10596.72 | T18: 5986.55 | V18: Deferred Tax Liabilities [Net] | W18: 0 | X18: 0 | Y18: 2303.87 | Z18: 0 | AA18: 0
A19: Reconciled Depreciation | B19: 16203.63 | C19: 14792.27 | D19: 13787.83 | E19: 12450.31 | F19: 10356.16 | H19: Total Non-Current Liabilities | I19: 1,62,497.02 | J19: 1,70,049.43 | K19: 1,61,613.83 | L19: 1,63,799.35 | M19: 1,56,721.55 | O19: Reconciled Depreciation | P19: 3931.33 | Q19: 3303.68 | R19: 3117.54 | S19: 3201.65 | T19: 3006.5 | V19: Other Long Term Liabilities | W19: 4272.92 | X19: 4557.12 | Y19: 4786.39 | Z19: 226.58 | AA19: 205.83
A20: EBIT | B20: 38554.26 | C20: 34864.73 | D20: 31038.98 | E20: 26665.91 | F20: 23705.33 | H20: CURRENT LIABILITIES | O20: EBIT | P20: 24179.6 | Q20: 11008.2 | R20: 10671.91 | S20: 7395.07 | T20: 2982.36 | V20: Long Term Provisions | W20: 149.03 | X20: 148.32 | Y20: 132.38 | Z20: 1.53 | AA20: 2.14
A21: Interest Expense | B21: 12048.21 | C21: 11156.06 | D21: 9315.98 | E21: 9224.14 | F21: 13348.04 | H21: Short Term Borrowings | I21: 39059.55 | J21: 28681.96 | K21: 23272.33 | L21: 12859.74 | M21: 14049.36 | O21: Interest Expense | P21: 3388.09 | Q21: 3333.5 | R21: 4094.78 | S21: 5106.33 | T21: 5244.97 | V21: Total Non-Current Liabilities | W21: 23123.08 | X21: 29515.12 | Y21: 37530.66 | Z21: 1158.67 | AA21: 3320.82
A22: Income/Profit Before Tax | B22: 26506.05 | C22: 23137.7 | D22: 19500.78 | E22: 14802.87 | F22: 16377.51 | H22: Trade Payables | I22: 9474.66 | J22: 12007.34 | K22: 9326.31 | L22: 7182.47 | M22: 9000.63 | O22: Income/Profit Before Tax | P22: 20791.51 | Q22: 7674.7 | R22: 6577.13 | S22: 2288.74 | T22: -2264.92 | V22: CURRENT LIABILITIES
A23: Income Tax Expense | B23: 6809.2 | C23: 6796.12 | D23: 5047.1 | E23: 2420.53 | F23: 9347.54 | H23: Other Current Liabilities | I23: 26002.07 | J23: 25288.4 | K23: 25137.5 | L23: 33116.29 | M23: 27687.3 | O23: Income Tax Expense | P23: -37.28 | Q23: -3051.94 | R23: 1665.55 | S23: 1018.76 | T23: 9.85 | V23: Short Term Borrowings | W23: 6758.99 | X23: 7827.72 | Y23: 9932.8 | Z23: 5293.17 | AA23: 2589.02
A24: Tax Provision | B24: 6809.2 | C24: 6796.12 | D24: 5047.1 | E24: 2420.53 | F24: 9347.54 | H24: Short Term Provisions | I24: 6376.21 | J24: 7470.25 | K24: 7095.76 | L24: 7276.05 | M24: 6639.17 | O24: Tax Provision | P24: -37.28 | Q24: -3051.94 | R24: 1665.55 | S24: 1018.76 | T24: 9.85 | V24: Trade Payables | W24: 2943.84 | X24: 2387.38 | Y24: 3448.56 | Z24: 13.26 | AA24: 712.32
A25: Net Income From Continuing Operation | B25: 19696.85 | C25: 16341.58 | D25: 14453.68 | E25: 12382.34 | F25: 7029.97 | H25: Total Current Liabilities | I25: 80912.49 | J25: 73447.95 | K25: 64831.9 | L25: 60434.55 | M25: 57376.46 | O25: Net Income From Continuing Operation | P25: 20828.79 | Q25: 10726.64 | R25: 4911.58 | S25: 1269.98 | T25: -2274.77 | V25: Other Current Liabilities | W25: 2698.93 | X25: 4695.52 | Y25: 2222.9 | Z25: 856.75 | AA25: 116.47
A26: Net Income | B26: 20811.89 | C26: 16912.55 | D26: 16675.9 | E26: 14634.63 | F26: 6728.22 | H26: Total Capital And Liabilities | I26: 3,93,294.53 | J26: 3,82,387.26 | K26: 3,54,496.80 | L26: 3,43,219.39 | M26: 3,27,667.45 | O26: Net Income | P26: 20828.79 | Q26: 10726.64 | R26: 4911.58 | S26: 1269.98 | T26: -2274.77 | V26: Short Term Provisions | W26: 14.57 | X26: 13.39 | Y26: 12.94 | Z26: 1.23 | AA26: 1.28
A27: Net Income Applicable to Common Share | B27: 20811.89 | C27: 16912.55 | D27: 16675.9 | E27: 14634.63 | F27: 11600.23 | H27: ASSETS | O27: Net Income Applicable to Common Share | P27: 20828.79 | Q27: 10726.64 | R27: 4911.58 | S27: 1269.98 | T27: -3159.02 | V27: Total Current Liabilities | W27: 12416.33 | X27: 14924.01 | Y27: 15617.2 | Z27: 6164.41 | AA27: 3419.09
A28: EPS (Earning Per Share) | B28: 21.46 | C28: 17.44 | D28: 17.2 | E28: 15.09 | H28: NON-CURRENT ASSETS | O28: EPS (Earning Per Share) | P28: 51.62 | Q28: 24.57 | R28: 9.63 | S28: 3.29 | T28: -5.9 | V28: Total Capital And Liabilities | W28: 75171.95 | X28: 72831.95 | Y28: 71766.18 | Z28: 24408.43 | AA28: 22530.29
H29: Tangible Assets | I29: 2,11,323.43 | J29: 1,96,441.71 | K29: 1,79,580.37 | L29: 1,63,892.12 | M29: 1,56,273.02 | V29: ASSETS
H30: Intangible Assets | I30: 427.69 | J30: 454.17 | K30: 485.41 | L30: 556.74 | M30: 538.28 | V30: NON-CURRENT ASSETS
H31: Capital Work-In-Progress | I31: 47153.81 | J31: 61743.88 | K31: 68598.66 | L31: 75343.6 | M31: 73066.76 | V31: Tangible Assets | W31: 43638.07 | X31: 46380.45 | Y31: 49139.79 | Z31: 540.93 | AA31: 569.26
H32: Intangible Assets Under Development | I32: 3.19 | J32: 44.92 | K32: 98.47 | L32: 94.9 | M32: 292.52 | V32: Intangible Assets | W32: 200.74 | X32: 202.34 | Y32: 202.49 | Z32: 0.06 | AA32: 0.82
H33: Other Assets | I33: 859.9 | J33: 465.18 | K33: 0 | L33: 0 | M33: 0 | V33: Capital Work-In-Progress | W33: 739.49 | X33: 188.33 | Y33: 184.3 | Z33: 0.67 | AA33: 0.13
H34: Fixed Assets | I34: 2,59,768.02 | J34: 2,59,149.86 | K34: 2,48,762.91 | L34: 2,39,887.36 | M34: 2,30,170.58 | V34: Fixed Assets | W34: 44578.3 | X34: 46771.12 | Y34: 49526.58 | Z34: 541.66 | AA34: 570.21
H35: Non-Current Investments | I35: 33107.93 | J35: 29719.75 | K35: 29881.07 | L35: 28125.65 | M35: 26400.89 | V35: Non-Current Investments | W35: 6906.84 | X35: 6373.48 | Y35: 4658.49 | Z35: 19358.65 | AA35: 18216.25
H36: Long Term Loans And Advances | I36: 800.66 | J36: 1233.47 | K36: 1288.4 | L36: 1498.12 | M36: 600.26 | V36: Deferred Tax Assets [Net] | W36: 376.34 | X36: 0 | Y36: 0 | Z36: 0 | AA36: 0
H37: Other Non-Current Assets | I37: 13734.78 | J37: 15676.35 | K37: 13101.2 | L37: 14978.86 | M37: 12547.78 | V37: Long Term Loans And Advances | W37: 1555.23 | X37: 1251.78 | Y37: 609.54 | Z37: 3583.2 | AA37: 3230.92
H38: Total Non-Current Assets | I38: 3,07,411.39 | J38: 3,05,779.43 | K38: 2,93,033.58 | L38: 2,84,489.99 | M38: 2,69,719.51 | V38: Other Non-Current Assets | W38: 1104.42 | X38: 1237.44 | Y38: 1421.66 | Z38: 24.29 | AA38: 34.95
H39: CURRENT ASSETS | V39: Total Non-Current Assets | W39: 54521.13 | X39: 55633.82 | Y39: 56216.27 | Z39: 23507.8 | AA39: 22052.33
H40: Current Investments | I40: 50 | J40: 50 | K40: 0 | L40: 499.99 | M40: 0 | V40: CURRENT ASSETS
H41: Inventories | I41: 17369.83 | J41: 13679.75 | K41: 9487.21 | L41: 9178.94 | M41: 10731.86 | V41: Current Investments | W41: 373.5 | X41: 0 | Y41: 175.01 | Z41: 0 | AA41: 0
H42: Trade Receivables | I42: 27347.52 | J42: 24741.45 | K42: 22293.32 | L42: 13701.72 | M42: 15668.11 | V42: Inventories | W42: 3474.89 | X42: 2324.07 | Y42: 2208.07 | Z42: 2.54 | AA42: 4.06
H43: Cash And Cash Equivalents | I43: 4600.5 | J43: 3741.73 | K43: 2455.59 | L43: 2338.46 | M43: 2209.11 | V43: Trade Receivables | W43: 6695.19 | X43: 11380.93 | Y43: 9490.01 | Z43: 9.65 | AA43: 366.81
H44: Short Term Loans And Advances | I44: 415.85 | J44: 312.45 | K44: 477.7 | L44: 416.82 | M44: 308.56 | V44: Cash And Cash Equivalents | W44: 5693.72 | X44: 1692.34 | Y44: 2014.95 | Z44: 86.61 | AA44: 101.02
H45: OtherCurrentAssets | I45: 36099.44 | J45: 34082.45 | K45: 26749.4 | L45: 32593.47 | M45: 29030.3 | V45: Short Term Loans And Advances | W45: 2820.67 | X45: 3.06 | Y45: 3.18 | Z45: 3.96 | AA45: 0.22
H46: Total Current Assets | I46: 85883.14 | J46: 76607.83 | K46: 61463.22 | L46: 58729.4 | M46: 57947.94 | V46: OtherCurrentAssets | W46: 1592.85 | X46: 1797.73 | Y46: 1658.69 | Z46: 797.87 | AA46: 5.85
H47: Total Assets | I47: 3,93,294.53 | J47: 3,82,387.26 | K47: 3,54,496.80 | L47: 3,43,219.39 | M47: 3,27,667.45 | V47: Total Current Assets | W47: 20650.82 | X47: 17198.13 | Y47: 15549.91 | Z47: 900.63 | AA47: 477.96
A52: TATA POWER
A54: Income Statement | H54: Balance sheet | O54: JSW
B55: 45740 | C55: 45739 | D55: 45738 | E55: 45737 | F55: 45736 | I55: 45740 | J55: 45739 | K55: 45738 | L55: 45737 | M55: 45736
O56: Income Statement | V56: Balance sheet
A57: Total Revenue/Income | B57: 61448.9 | C57: 55109.08 | D57: 42815.67 | E57: 32468.1 | F57: 28147.6 | H57: EQUITIES AND LIABILITIES | P57: 45740 | Q57: 45739 | R57: 45738 | S57: 45737 | T57: 45736 | W57: 45740 | X57: 45739 | Y57: 45738 | Z57: 45737 | AA57: 45736
A58: Total Other Income Expense Net | B58: -2443.01 | C58: -4371.65 | D58: -1385.97 | E58: 2231.36 | F58: 0 | H58: SHAREHOLDER'S FUNDS
A59: Total Operating Expense | B59: 59084.66 | C59: 55213.61 | D59: 42285.72 | E59: 32295.75 | F59: 23551.82 | H59: Equity Share Capital | I59: 319.56 | J59: 319.56 | K59: 319.56 | L59: 319.56 | M59: 270.5 | O59: Total Revenue/Income | P59: 175006 | Q59: 165960 | R59: 146371 | S59: 79839 | T59: 73326 | V59: EQUITIES AND LIABILITIES
A60: Tax Provision | B60: 1451.92 | C60: 1647.33 | D60: 379.56 | E60: 501.88 | F60: 800.74 | H60: Total Share Capital | I60: 319.56 | J60: 319.56 | K60: 319.56 | L60: 319.56 | M60: 270.5 | O60: Cost Of Revenue | P60: 129568 | Q60: 118243 | R60: 84453 | S60: 42788 | T60: 49434 | V60: SHAREHOLDER'S FUNDS
A61: Selling General Administrative Expenses | B61: 0 | C61: 402.86 | D61: 323.93 | E61: 221.75 | F61: 1879 | H61: Reserves and Surplus | I61: 15468.1 | J61: 13380.03 | K61: 10560.24 | L61: 16559 | M61: 13491.47 | O61: Gross Profit | P61: 45438 | Q61: 45403 | R61: 61918 | S61: 35271 | T61: 23892 | V61: Equity Share Capital | W61: 305 | X61: 301 | Y61: 301 | Z61: 302 | AA61: 301
A62: Sell And Marketing Exp | B62: 0 | C62: 1.33 | D62: 0 | E62: 3.07 | F62: 0 | H62: Total Reserves and Surplus | I62: 15468.1 | J62: 13380.03 | K62: 10560.24 | L62: 16559 | M62: 13491.47 | O62: Total Operating Expense | P62: 163047 | Q62: 161789 | R62: 118333 | S62: 68334 | T62: 69964 | V62: Total Share Capital | W62: 305 | X62: 301 | Y62: 301 | Z62: 302 | AA62: 301
A63: Research & Development | B63: 12.2 | C63: 17.06 | D63: 0 | E63: 0 | F63: 0 | H63: Total Shareholders Funds | I63: 15787.66 | J63: 13699.59 | K63: 10879.8 | L63: 16878.56 | M63: 13761.97 | O63: Selling General Administrative Expenses | P63: 0 | Q63: 3915 | R63: 3493 | S63: 196 | T63: 4577 | V63: Reserves and Surplus | W63: 74978 | X63: 63358 | Y63: 63200 | Z63: 46675 | AA63: 38061
A64: Reconciled Depreciation | B64: 3786.37 | C64: 3439.2 | D64: 3122.2 | E64: 2744.94 | F64: 2633.56 | H64: Hybrid/Debt/Other Securities | I64: 0 | J64: 0 | K64: 0 | L64: 1500 | M64: 1500 | O64: Other Operating Expenses | P64: 163047 | Q64: 149801 | R64: 44601 | S64: 24684 | T64: 19884 | V64: Total Reserves and Surplus | W64: 74978 | X64: 63358 | Y64: 63200 | Z64: 46675 | AA64: 38061
A65: Other Operating Expenses | B65: 59072.46 | C65: 54792.36 | D65: 4060.42 | E65: 2812.48 | F65: 1358.75 | H65: NON-CURRENT LIABILITIES | O65: Sell And Marketing Exp | P65: 0 | Q65: 8028 | R65: 0 | S65: 4166 | T65: 0 | V65: Total Shareholders Funds | W65: 75283 | X65: 63659 | Y65: 63501 | Z65: 46977 | AA65: 38362
A66: Operating Income/Profit | B66: 2364.24 | C66: 4267.12 | D66: 529.95 | E66: 172.35 | F66: 5463.71 | H66: Long Term Borrowings | I66: 13373.21 | J66: 11272.3 | K66: 18087.97 | L66: 13168.52 | M66: 9825.33 | O66: Research & Development | P66: 0 | Q66: 45 | R66: 0 | S66: 0 | T66: 0 | V66: NON-CURRENT LIABILITIES
A67: Net Income From Continuing Operation | B67: 3102.53 | C67: 400.2 | D67: 680.61 | E67: 611.46 | F67: 1726.67 | H67: Deferred Tax Liabilities [Net] | I67: 996.19 | J67: 617.29 | K67: 0 | L67: 135.36 | M67: 307.25 | O67: Depreciation And Amortization | P67: 8172 | Q67: 7474 | R67: 6001 | S67: 4679 | T67: 4246 | V67: Long Term Borrowings | W67: 47241 | X67: 48346 | Y67: 41176 | Z67: 39551 | AA67: 39247
A68: Net Income Applicable to Common Share | B68: 3102.53 | C68: 3336.44 | D68: 1741.46 | E68: 1127.38 | F68: 846.38 | H68: Other Long Term Liabilities | I68: 3739.35 | J68: 3728.83 | K68: 3325.33 | L68: 377.51 | M68: 412.97 | O68: Operating Income/Profit | P68: 11959 | Q68: 11073 | R68: 28038 | S68: 11505 | T68: 3362 | V68: Deferred Tax Liabilities [Net] | W68: 9320 | X68: 7460 | Y68: 6935 | Z68: 3095 | AA68: 1315
A69: Net Income | B69: 3102.53 | C69: 3336.44 | D69: 1741.46 | E69: 1127.38 | F69: 1017.38 | H69: Long Term Provisions | I69: 280.7 | J69: 285.94 | K69: 274 | L69: 261.38 | M69: 222.46 | O69: Interest Income | P69: 0 | Q69: -7174 | R69: 4051 | S69: 3956 | T69: -4463 | V69: Other Long Term Liabilities | W69: 2852 | X69: 2791 | Y69: 3832 | Z69: 5816 | AA69: 7202
A70: Interest Income | B70: 0 | C70: 513.65 | D70: 292.5 | E70: 3137 | F70: -3226.62 | H70: Total Non-Current Liabilities | I70: 18389.45 | J70: 15904.36 | K70: 21687.3 | L70: 13942.77 | M70: 10768.01 | O70: Total Other Income Expense Net | P70: -6512 | Q70: -6311 | R70: -3261 | S70: 3382 | T70: 0 | V70: Long Term Provisions | W70: 1288 | X70: 1250 | Y70: 1292 | Z70: 753 | AA70: 322
A71: Interest Expense | B71: 4633.22 | C71: 4371.65 | D71: 3859.02 | E71: 4010.39 | F71: 4321 | H71: CURRENT LIABILITIES | O71: EBITDA | P71: 29829 | Q71: 20036 | R71: 39797 | S71: 20650 | T71: 11614 | V71: Total Non-Current Liabilities | W71: 60701 | X71: 59847 | Y71: 53235 | Z71: 49215 | AA71: 48086
A72: Income/Profit Before Tax | B72: 4554.45 | C72: 2047.53 | D72: 1060.17 | E72: 1113.34 | F72: 2368.16 | H72: Short Term Borrowings | I72: 6152.95 | J72: 10593.18 | K72: 6620.41 | L72: 5595.7 | M72: 6212.31 | O72: Reconciled Depreciation | P72: 8172 | Q72: 7474 | R72: 6001 | S72: 4679 | T72: 4246 | V72: CURRENT LIABILITIES
A73: Income Tax Expense | B73: 1451.92 | C73: 1647.33 | D73: 379.56 | E73: 501.88 | F73: 622.18 | H73: Trade Payables | I73: 4081.38 | J73: 1985.02 | K73: 4079.89 | L73: 1137 | M73: 1001.87 | O73: EBIT | P73: 21657 | Q73: 12562 | R73: 33796 | S73: 15971 | T73: 7368 | V73: Short Term Borrowings | W73: 11582 | X73: 6825 | Y73: 9259 | Z73: 1285 | AA73: 6813
A74: Gross Profit | B74: 20707.29 | C74: 17105.89 | D74: 15183.22 | E74: 10788.22 | F74: 10650.09 | H74: Other Current Liabilities | I74: 6049.69 | J74: 5972.8 | K74: 3841.41 | L74: 3789.55 | M74: 4310.3 | O74: Interest Expense | P74: 8105 | Q74: 6902 | R74: 4968 | S74: 3957 | T74: 4265 | V74: Trade Payables | W74: 12742 | X74: 30705 | Y74: 24328 | Z74: 12150 | AA74: 13354
A75: Extraordinary Items | B75: 0 | C75: 0 | D75: -467.83 | E75: -46.2 | F75: -250.98 | H75: Short Term Provisions | I75: 27.82 | J75: 17.76 | K75: 44.59 | L75: 25.37 | M75: 62.02 | O75: Income/Profit Before Tax | P75: 13552 | Q75: 5792 | R75: 28828 | S75: 12014 | T75: 3103 | V75: Other Current Liabilities | W75: 24754 | X75: 11570 | Y75: 12320 | Z75: 23362 | AA75: 15363
A76: EPS (Earning Per Share) | B76: 11.56 | C76: 10.43 | D76: 43.87 | E76: 3.53 | F76: 3.76 | H76: Total Current Liabilities | I76: 16311.84 | J76: 18568.76 | K76: 14586.3 | L76: 10547.62 | M76: 11586.5 | O76: Income Tax Expense | P76: 4407 | Q76: 1516 | R76: 8807 | S76: 4142 | T76: -906 | V76: Short Term Provisions | W76: 376 | X76: 235 | Y76: 227 | Z76: 243 | AA76: 64
A77: EBITDA | B77: 12974.04 | C77: 12794.62 | D77: 8041.39 | E77: 7868.67 | F77: 9322.72 | H77: Total Capital And Liabilities | I77: 50488.95 | J77: 48172.71 | K77: 47153.4 | L77: 42868.95 | M77: 37616.48 | O77: Tax Provision | P77: 4407 | Q77: 1516 | R77: 8807 | S77: 4142 | T77: 1417 | V77: Total Current Liabilities | W77: 49454 | X77: 49335 | Y77: 46134 | Z77: 37040 | AA77: 35594
A78: EBIT | B78: 9187.67 | C78: 9353.36 | D78: 4919.19 | E78: 5123.73 | F78: 6689.16 | H78: ASSETS | O78: Net Income From Continuing Operation | P78: 9145 | Q78: 4276 | R78: 20021 | S78: 7872 | T78: 4009 | V78: Total Capital And Liabilities | W78: 1,85,438.00 | X78: 1,72,841.00 | Y78: 1,62,870.00 | Z78: 1,33,232.00 | AA78: 1,22,042.00
A79: Discontinued Operations | B79: 0 | C79: 0 | D79: -467.83 | E79: -46.2 | F79: -410.23 | H79: NON-CURRENT ASSETS | O79: Extraordinary Items | P79: 0 | Q79: 0 | R79: 0 | S79: 0 | T79: 2323 | V79: ASSETS
A80: Depreciation And Amortization | B80: 3786.37 | C80: 3439.2 | D80: 3122.2 | E80: 2746.06 | F80: 2633.56 | H80: Tangible Assets | I80: 23522.28 | J80: 23699.59 | K80: 23708.53 | L80: 8200.75 | M80: 7974.07 | O80: Net Income | P80: 8812 | Q80: 4144 | R80: 20665 | S80: 7911 | T80: 4030 | V80: NON-CURRENT ASSETS
A81: Cost Of Revenue | B81: 40741.61 | C81: 38003.19 | D81: 27632.45 | E81: 21577.12 | F81: 7917.72 | H81: Intangible Assets | I81: 19.99 | J81: 22.46 | K81: 37.43 | L81: 55.39 | M81: 62.22 | O81: Net Income Applicable to Common Share | P81: 8812 | Q81: 4144 | R81: 20665 | S81: 7911 | T81: 4030 | V81: Tangible Assets | W81: 77243 | X81: 73255 | Y81: 69767 | Z81: 50328 | AA81: 50219
H82: Capital Work-In-Progress | I82: 1798.53 | J82: 1272.56 | K82: 965.15 | L82: 285.45 | M82: 402.87 | O82: EPS (Earning Per Share) | P82: 36.34 | Q82: 17.25 | R82: 85.96 | S82: 32.91 | T82: 16.78 | V82: Intangible Assets | W82: 2343 | X82: 1801 | Y82: 1879 | Z82: 1614 | AA82: 323
H83: Fixed Assets | I83: 25340.8 | J83: 24994.61 | K83: 24711.11 | L83: 8541.59 | M83: 8439.16 | V83: Capital Work-In-Progress | W83: 10504 | X83: 10271 | Y83: 12459 | Z83: 28914 | AA83: 23810
H84: Non-Current Investments | I84: 13013.8 | J84: 12064.55 | K84: 10711.38 | L84: 26128.4 | M84: 21327.2 | V84: Intangible Assets Under Development | W84: 352 | X84: 235 | Y84: 140 | Z84: 128 | AA84: 331
H85: Deferred Tax Assets [Net] | I85: 0 | J85: 0 | K85: 250 | L85: 0 | M85: 0 | V85: Fixed Assets | W85: 90442 | X85: 85562 | Y85: 84245 | Z85: 80984 | AA85: 74683
H86: Long Term Loans And Advances | I86: 4.25 | J86: 2.68 | K86: 453.17 | L86: 490.18 | M86: 42.1 | V86: Non-Current Investments | W86: 30141 | X86: 24320 | Y86: 18028 | Z86: 12458 | AA86: 5999
H87: Other Non-Current Assets | I87: 3952.76 | J87: 3011.41 | K87: 2605.66 | L87: 2463.95 | M87: 1920.44 | V87: Long Term Loans And Advances | W87: 11501 | X87: 5346 | Y87: 5763 | Z87: 5382 | AA87: 8705
H88: Total Non-Current Assets | I88: 42311.61 | J88: 40073.25 | K88: 38731.32 | L88: 37624.12 | M88: 31728.9 | V88: Other Non-Current Assets | W88: 10260 | X88: 8469 | Y88: 7349 | Z88: 4705 | AA88: 3280
H89: CURRENT ASSETS | V89: Total Non-Current Assets | W89: 1,42,344.00 | X89: 1,23,697.00 | Y89: 1,15,385.00 | Z89: 1,03,529.00 | AA89: 92667
H90: Current Investments | I90: 392.4 | J90: 64.17 | K90: 67.6 | L90: 240.01 | M90: 20 | V90: CURRENT ASSETS
H91: Inventories | I91: 2119.53 | J91: 2457.95 | K91: 2292.33 | L91: 632.94 | M91: 635.01 | V91: Inventories | W91: 23234 | X91: 19517 | Y91: 21028 | Z91: 10692 | AA91: 9623
H92: Trade Receivables | I92: 1742.08 | J92: 2020.9 | K92: 1085.51 | L92: 910.87 | M92: 1108.68 | V92: Trade Receivables | W92: 6498 | X92: 6000 | Y92: 6146 | Z92: 3333 | AA92: 3166
H93: Cash And Cash Equivalents | I93: 618.59 | J93: 295.92 | K93: 78.55 | L93: 142.67 | M93: 178.94 | V93: Cash And Cash Equivalents | W93: 8129 | X93: 18716 | Y93: 15527 | Z93: 11746 | AA93: 11401
H94: Short Term Loans And Advances | I94: 0 | J94: 0 | K94: 1328.48 | L94: 1523.89 | M94: 550.09 | V94: Short Term Loans And Advances | W94: 4 | X94: 93 | Y94: 265 | Z94: 733 | AA94: 321
H95: OtherCurrentAssets | I95: 3304.74 | J95: 3260.52 | K95: 3569.61 | L95: 1794.45 | M95: 3394.86 | V95: OtherCurrentAssets | W95: 5229 | X95: 4818 | Y95: 4519 | Z95: 3199 | AA95: 4864
H96: Total Current Assets | I96: 8177.34 | J96: 8099.46 | K96: 8422.08 | L96: 5244.83 | M96: 5887.58 | V96: Total Current Assets | W96: 43094 | X96: 49144 | Y96: 47485 | Z96: 29703 | AA96: 29375
H97: Total Assets | I97: 50488.95 | J97: 48172.71 | K97: 47153.4 | L97: 42868.95 | M97: 37616.48 | V97: Total Assets | W97: 1,85,438.00 | X97: 1,72,841.00 | Y97: 1,62,870.00 | Z97: 1,33,232.00 | AA97: 1,22,042.00
A104: POWERGRID | O104: NHPC
A106: Income Statement | H106: Balance sheet | O106: Income Statement | V106: Balance sheet
B107: 45740 | C107: 45739 | D107: 45738 | E107: 45737 | F107: 45736 | I107: 45740 | J107: 45739 | K107: 45738 | L107: 45737 | M107: 45736 | P107: 45740 | Q107: 45739 | R107: 45738 | S107: 45737 | T107: 45736 | W107: 45740 | X107: 45739 | Y107: 45738 | Z107: 45737 | AA107: 45736
A109: Total Revenue/Income | B109: 45843.1 | C109: 45581.28 | D109: 41616.34 | E109: 39639.79 | F109: 35588.11 | H109: EQUITIES AND LIABILITIES | O109: Total Revenue/Income | P109: 9632.16 | Q109: 10607.4 | R109: 9188.78 | S109: 9647.89 | T109: 10008.07 | V109: EQUITIES AND LIABILITIES
A110: Cost Of Revenue | B110: 19035.48 | C110: 448.07 | D110: 1315.66 | E110: 1170.29 | F110: 385.32 | H110: SHAREHOLDER'S FUNDS | O110: Cost Of Revenue | P110: 3418.43 | Q110: 939.56 | R110: 888.7 | S110: 1390.59 | T110: 1138.46 | V110: SHAREHOLDER'S FUNDS
A111: Gross Profit | B111: 26807.62 | C111: 45581.28 | D111: 39519.64 | E111: 38138.13 | F111: 35663.44 | H111: Equity Share Capital | I111: 9300.6 | J111: 6975.45 | K111: 6975.45 | L111: 5231.59 | M111: 5231.59 | O111: Gross Profit | P111: 6213.73 | Q111: 9667.84 | R111: 8300.08 | S111: 8101.7 | T111: 8869.61 | V111: Equity Share Capital | W111: 10045.03 | X111: 10045.03 | Y111: 10045.03 | Z111: 10045.03 | AA111: 10045.03
A112: Total Operating Expense | B112: 27808.23 | C112: 29070.47 | D112: 25957.32 | E112: 24820.56 | F112: 15762.02 | H112: Total Share Capital | I112: 9300.6 | J112: 6975.45 | K112: 6975.45 | L112: 5231.59 | M112: 5231.59 | O112: Total Operating Expense | P112: 6350.39 | Q112: 6028.22 | R112: 5724.01 | S112: 6248.79 | T112: 5990.03 | V112: Total Share Capital | W112: 10045.03 | X112: 10045.03 | Y112: 10045.03 | Z112: 10045.03 | AA112: 10045.03
A113: Selling General Administrative Expenses | B113: 0 | C113: 4023.34 | D113: 2243.89 | E113: 273.09 | F113: 3206.04 | H113: Reserves and Surplus | I113: 77566.45 | J113: 75857.51 | K113: 69176.12 | L113: 64347.25 | M113: 59208.1 | O113: Selling General Administrative Expenses | P113: 0 | Q113: 1435.28 | R113: 1554.76 | S113: 437.1 | T113: 3320.97 | V113: Reserves and Surplus | W113: 27223.58 | X113: 25362.93 | Y113: 23441.07 | Z113: 21602.28 | AA113: 19938.78
A114: Other Operating Expenses | B114: 27808.23 | C114: 25022.66 | D114: 1380 | E114: 16256.44 | F114: 1071.87 | H114: Total Reserves and Surplus | I114: 77566.45 | J114: 75857.51 | K114: 69176.12 | L114: 64347.25 | M114: 59208.1 | O114: Other Operating Expenses | P114: 6350.39 | Q114: 4570.58 | R114: 1557.97 | S114: 1405 | T114: 1157.7 | V114: Total Reserves and Surplus | W114: 27223.58 | X114: 25362.93 | Y114: 23441.07 | Z114: 21602.28 | AA114: 19938.78
A115: Sell And Marketing Exp | B115: 0 | C115: 17.24 | D115: 0 | E115: 7.38 | F115: 0 | H115: Total Shareholders Funds | I115: 86867.05 | J115: 82832.96 | K115: 76151.57 | L115: 69578.84 | M115: 64439.69 | O115: Sell And Marketing Exp | P115: 0 | Q115: 11.06 | R115: 0 | S115: 4.73 | T115: 0 | V115: Total Shareholders Funds | W115: 37268.61 | X115: 35407.96 | Y115: 33486.1 | Z115: 31647.31 | AA115: 29983.81
...
